Jlab/__init__.py
Jlab/aes_crypt.py
Jlab/finlab_data.py
Jlab/plot.py
Jlab/redis_sync.py
Jlab/shioaji_wrapper.py
Jlab/strategymetrics.py
Jlab/utils.py
Jlab/watcher.py
Jlab-1.1.88.dist-info/LICENSE.txt
Jlab-1.1.88.dist-info/METADATA
Jlab-1.1.88.dist-info/WHEEL
Jlab-1.1.88.dist-info/top_level.txt
Jlab-1.1.88.dist-info/RECORD
