Metadata-Version: 2.1
Name: Jlab
Version: 1.1.88
Summary: Jlab is a package for data analysis
Author: twfxjjbw
Author-email: twfxjjbw@gmail.com
Classifier: Programming Language :: Python :: 3.7
Classifier: Programming Language :: Python :: 3.8
Classifier: Programming Language :: Python :: 3.9
Classifier: Programming Language :: Python :: 3.10
Classifier: Programming Language :: Python :: 3.11
Classifier: License :: OSI Approved :: MIT License
Classifier: Operating System :: OS Independent
Requires-Python: >=3.7
License-File: LICENSE.txt
Requires-Dist: retry
Requires-Dist: PyGithub
Requires-Dist: pycryptodome
Requires-Dist: wget
Requires-Dist: plotly
Requires-Dist: loguru
Requires-Dist: redis
Requires-Dist: py7zr
